Topsis_Ishan_102103408/__init__.py
Topsis_Ishan_102103408/topsis.py
Topsis_Ishan_102103408-1.0.0.dist-info/LICENSE
Topsis_Ishan_102103408-1.0.0.dist-info/METADATA
Topsis_Ishan_102103408-1.0.0.dist-info/WHEEL
Topsis_Ishan_102103408-1.0.0.dist-info/top_level.txt
Topsis_Ishan_102103408-1.0.0.dist-info/RECORD
