Metadata-Version: 2.1
Name: Topsis-Ishan-102103408
Version: 1.0.0
Summary: Implementation of Topsis
Author: Ishan Mathur
Author-email: imathur_be21@thapar.edu
License: MIT License
Keywords: Topsis
Classifier: Development Status :: 3 - Alpha
Classifier: License :: OSI Approved :: MIT License
Classifier: Operating System :: OS Independent
Classifier: Intended Audience :: Developers
Classifier: Programming Language :: Python :: 3
License-File: LICENSE
Requires-Dist: pandas
Requires-Dist: numpy
